toolbox_view/__init__.py
toolbox_view/apps.py
toolbox_view/bulk_save.py
toolbox_view/helpers.py
toolbox_view/modal_confirm.py
toolbox_view/report.py
toolbox_view/tasks.py
toolbox_view/toolbox_base.py
toolbox_view/urls.py
toolbox_view/views.py
toolbox_view/templates/toolbox/base.html
django_toolbox_view-0.0.6.dist-info/LICENSE
django_toolbox_view-0.0.6.dist-info/METADATA
django_toolbox_view-0.0.6.dist-info/WHEEL
django_toolbox_view-0.0.6.dist-info/top_level.txt
django_toolbox_view-0.0.6.dist-info/RECORD
