Metadata-Version: 2.1
Name: django-toolbox-view
Version: 0.0.6
Summary: Provides a Django view to run functions from apps
Author: Ian Jones
License: MIT License
Project-URL: Homepage, https://github.com/jonesim/django-toolbox-view
Classifier: License :: OSI Approved :: MIT License
Classifier: Programming Language :: Python
Classifier: Programming Language :: Python :: 3
Requires-Python: >=3.9
License-File: LICENSE
Requires-Dist: django-nested-modals
Requires-Dist: django-tab-menus
